picmistandard/__init__.py
picmistandard/applied_fields.py
picmistandard/base.py
picmistandard/diagnostics.py
picmistandard/fields.py
picmistandard/interactions.py
picmistandard/lasers.py
picmistandard/particles.py
picmistandard/simulation.py
picmistandard/version.py
picmistandard-0.33.0.dist-info/METADATA
picmistandard-0.33.0.dist-info/WHEEL
picmistandard-0.33.0.dist-info/top_level.txt
picmistandard-0.33.0.dist-info/RECORD
