Metadata-Version: 2.1
Name: picmistandard
Version: 0.33.0
Summary: Python base classes for PICMI standard
License: PICMI/AMI v0.0.1 Copyright (c) 2018, The Regents of the University of California, through Lawrence Berkeley National Laboratory, and Lawrence Livermore National Security, LLC, for the operation of Lawrence Livermore National Laboratory (subject to receipt of any required approvals from the U.S. Dept. of Energy). All rights reserved.
Project-URL: Repository, https://github.com/picmi-standard/picmi
Project-URL: Documentation, https://picmi.readthedocs.io/en/latest
Classifier: Development Status :: 4 - Beta
Classifier: Programming Language :: Python :: 3
Classifier: Intended Audience :: Developers
Classifier: Topic :: Scientific/Engineering
Classifier: Topic :: Software Development :: User Interfaces
Requires-Dist: numpy >=1.15
Requires-Dist: scipy ~=1.5
